aidataup/__init__.py
aidataup/cleans/clean_thailand_car_plateno.py
aidataup/convert/convert_num_th_to_global.py
aidataup/extract/extract_api.py
aidataup/utils/database_manager.py
aidataup/utils/connector/connector_mysql.py
aidataup/utils/connector/connector_postgresql.py
aidataup/utils/connector/connector_sqlite.py
aidataup/verify/verify_citizenid.py
aidataup/verify/verify_datetime.py
aidataup/verify/verify_email.py
aidataup/verify/verify_phone.py
aidataup-0.0.6.dist-info/METADATA
aidataup-0.0.6.dist-info/WHEEL
aidataup-0.0.6.dist-info/licenses/LICENSE
aidataup-0.0.6.dist-info/RECORD
