Metadata-Version: 2.3
Name: aidataup
Version: 0.0.6
Summary: aidataup
Author-email: dData <user@data.co.th>
License-File: LICENSE
Classifier: License :: OSI Approved :: MIT License
Classifier: Operating System :: OS Independent
Classifier: Programming Language :: Python :: 3
Requires-Python: >=3.10
Requires-Dist: mysql-connector-python
Requires-Dist: pandas>=2.0.0
Requires-Dist: phonenumbers>=8.12.50
Requires-Dist: psycopg2
Requires-Dist: requests
